{"stats":{"minecraft:custom":{"minecraft:time_since_rest":208908,"minecraft:crouch_one_cm":204,"minecraft:sprint_one_cm":19842,"minecraft:play_time":225866,"minecraft:deaths":15,"minecraft:damage_taken":4260,"minecraft:walk_one_cm":29659,"minecraft:sneak_time":121,"minecraft:jump":192,"minecraft:damage_dealt":565,"minecraft:leave_game":20,"minecraft:time_since_death":208901,"minecraft:total_world_time":225866,"minecraft:fall_one_cm":5533,"minecraft:fly_one_cm":45924},"minecraft:picked_up":{"minecraft:arrow":2,"minecraft:bone":2,"minecraft:wheat_seeds":3},"minecraft:killed_by":{"minecraft:vindicator":2,"minecraft:zombie":2,"minecraft:pillager":11},"minecraft:used":{"alexsmobs:animal_dictionary":1},"minecraft:mined":{"gravestone:gravestone":4,"minecraft:grass":11,"minecraft:tall_grass":12}},"DataVersion":3465}